{
  "characters_present": [
    {
      "canonical_name": "Swann",
      "surface_forms": [
        "Swann"
      ],
      "presence_type": "explicit",
      "presence_confidence": 0.99
    }
  ],
  "appraisal_events": [
    {
      "event_id": "E1",
      "source": "collective_social_voice",
      "target": "Swann",
      "type": "prestige_association",
      "polarity": "positive",
      "narrative_stance": "neutral_report",
      "confidence": 0.82,
      "evidence": "« Je déjeune justement demain avec le Préfet de police à l'Élysée. » / « Oui, chez M. Grévy, » et Swann est « un peu gêné de l'effet que sa phrase avait produit. »",
      "explanation": "Swann’s mention of dining at the Élysée with high officials reveals elite associations that the group registers as impressive, heightening his local prestige."
    }
  ],
  "status_effects": [
    {
      "character": "Swann",
      "dimension": "social_status",
      "delta": 1,
      "based_on_events": [
        "E1"
      ],
      "confidence": 0.82,
      "explanation": "His elite connections are exposed and socially registered, boosting his perceived status despite his slight embarrassment."
    }
  ],
  "ambiguities": [],
  "unit_id": "v1-p2-un-amour-de-swann#p-111-p-115"
}
