{
  "characters_present": [
    {
      "canonical_name": "baron de Charlus",
      "surface_forms": [
        "baron de Charlus"
      ],
      "presence_type": "explicit",
      "presence_confidence": 0.99
    }
  ],
  "appraisal_events": [
    {
      "event_id": "E1",
      "source": "narrator",
      "target": "baron de Charlus",
      "type": "narrated_diminishment",
      "polarity": "negative",
      "narrative_stance": "endorsed",
      "confidence": 0.88,
      "evidence": "Le narrateur souligne à quel point il a vieilli, détaille le fard et les moustaches teintes, note son brusque empressement intéressé envers Morel sans même le saluer, et compare sa manière d’aborder à celle de parents « levant » une femme, l’objet ayant « changé de sexe ».",
      "explanation": "Le baron est localement rabaissé par une description crûe de son vieillissement et par une conduite mondaine prédatrice et hautaine, présentée de façon ironique et peu flatteuse."
    }
  ],
  "status_effects": [
    {
      "character": "baron de Charlus",
      "dimension": "general_appraisal",
      "delta": -1,
      "based_on_events": [
        "E1"
      ],
      "confidence": 0.86,
      "explanation": "Il ressort amoindri par le portrait vieillissant et la conduite jugée déplacée et intéressée."
    }
  ],
  "ambiguities": [],
  "unit_id": "v4-p2#p-311-p-315"
}
