{
  "unit_id": "v7-p2-m-de-charlus-pendant-la-guerre#p-11-p-15",
  "source_text": "islt_fr",
  "chapter_id": "v7-p2-m-de-charlus-pendant-la-guerre",
  "paragraph_start": 11,
  "paragraph_end": 15,
  "raw_text": "Je dois, du reste, dire que la connaissance du mari d'Andrée n'était ni très facile ni très agréable à faire, et que l'amitié qu'on lui vouait était promise à bien des déceptions. Il était, en effet, à ce moment déjà fort malade et s'épargnait les fatigues autres que celles qui lui paraissaient devoir peut-être lui donner du plaisir. Or il ne classait parmi celles-là que les rendez-vous avec des gens qu'il ne connaissait pas encore et que son ardente imagination lui représentait sans doute comme ayant une chance d'être différents des autres. Mais pour ceux qu'il connaissait déjà, il savait trop bien comment ils étaient, comment ils seraient, ils ne lui paraissaient plus valoir la peine d'une fatigue dangereuse pour lui et peut-être mortelle. C'était, en somme, un très mauvais ami. Et peut-être dans son goût pour des gens nouveaux se retrouvait-il quelque chose de l'audace frénétique qu'il portait jadis, à Balbec, aux sports, au jeu, à tous les excès de table. Quant à Mme Verdurin, elle voulait à chaque fois me faire faire la connaissance d'Andrée, ne pouvant admettre que je l'eusse connue depuis longtemps. D'ailleurs Andrée venait rarement avec son mari, mais elle était pour moi une amie admirable et sincère. Fidèle à l'esthétique de son mari, qui était en réaction contre les Ballets russes, elle disait du marquis de Polignac : « Il a sa maison décorée par Bakst ; comment peut-on dormir là dedans, j'aimerais mieux Dubufe. »\n\nD'ailleurs les Verdurin, par le progrès fatal de l'esthétisme, qui finit par se manger la queue, disaient ne pas pouvoir supporter le modern style (de plus c'était munichois) ni les appartements blancs et n'aimaient plus que les vieux meubles français dans un décor sombre.\n\nOn fut très étonné à cette époque, où Mme Verdurin pouvait avoir chez elle qui elle voulait, de lui voir faire indirectement des avances à une personne qu'elle avait complètement perdue de vue, Odette. On trouvait qu'elle ne pourrait rien ajouter au brillant milieu qu'était devenu le petit groupe. Mais une séparation prolongée, en même temps qu'elle apaise les rancunes, réveille quelquefois l'amitié. Et puis le phénomène qui amène non seulement les mourants à ne prononcer que des noms autrefois familiers, mais les vieillards à se complaire dans leurs souvenirs d'enfance, ce phénomène a son équivalent social. Pour réussir dans l'entreprise de faire revenir Odette chez elle, Mme Verdurin n'employa pas, bien entendu, les « ultras », mais les habitués moins fidèles qui avaient gardé un pied dans l'un et l'autre salon. Elle leur disait : « Je ne sais pas pourquoi on ne la voit plus ici. Elle est peut-être brouillée, moi pas. En somme, qu'est-ce que je lui ai fait ? C'est chez moi qu'elle a connu ses deux maris. Si elle veut revenir, qu'elle sache que les portes lui sont ouvertes. » Ces paroles, qui auraient dû coûter à la fierté de la Patronne si elles ne lui avaient pas été dictées par son imagination, furent redites, mais sans succès. Mme Verdurin attendit Odette sans la voir venir, jusqu'à ce que des événements qu'on verra plus loin amenassent pour de tout autres raisons ce que n'avait pu l'ambassade pourtant zélée des lâcheurs. Tant il est peu de réussites faciles, et d'échecs définitifs.\n\nLes choses étaient tellement les mêmes, tout en paraissant différentes, qu'on retrouvait tout naturellement les mots d'autrefois : « bien pensants, mal pensants ». Et de même que les anciens communards avaient été antirévisionnistes, les plus grands dreyfusards voulaient faire fusiller tout le monde et avaient l'appui des généraux, comme ceux-ci au temps de l'affaire avaient été contre Galliffet. À ces réunions, Mme Verdurin invitait quelques dames un peu récentes, connues par les oeuvres et qui les premières fois venaient avec des toilettes éclatantes, de grands colliers de perles qu'Odette, qui en avait un aussi beau, de l'exhibition duquel elle-même avait abusé, regardait, maintenant qu'elle était en « tenue de guerre » à l'imitation des dames du faubourg, avec sévérité. Mais les femmes savent s'adapter. Au bout de trois ou quatre fois elles se rendaient compte que les toilettes qu'elles avaient crues chic étaient précisément proscrites par les personnes qui l'étaient, elles mettaient de côté leurs robes d'or et se résignaient à la simplicité.\n\nMme Verdurin disait : « C'est désolant, je vais téléphoner à Bontemps de faire le nécessaire pour demain, on a encore « caviardé » toute la fin de l'article de Norpois et simplement parce qu'il laissait entendre qu'on avait « limogé » Percin. » Car la bêtise courante faisait que chacun tirait sa gloire d'user des expressions courantes, et croyait montrer qu'elle était ainsi à la mode comme faisait une bourgeoise en disant, quand on parlait de M. de Bréauté ou de Charlus : « Qui ? Bebel de Bréauté, Mémé de Charlus ? » Les duchesses font de même, d'ailleurs, et avaient le même plaisir à dire « limoger » car, chez les duchesses, c'est, pour les roturiers un peu poètes, le nom qui diffère, mais elles s'expriment selon la catégorie d'esprit à laquelle elles appartiennent et où il y a aussi énormément de bourgeois. Les classes d'esprit n'ont pas égard à la naissance.",
  "preprocessed_text": "Je dois, du reste, dire que la connaissance du mari d'Andrée n'était ni très facile ni très agréable à faire, et que l'amitié qu'on lui vouait était promise à bien des déceptions. Il était, en effet, à ce moment déjà fort malade et s'épargnait les fatigues autres que celles qui lui paraissaient devoir peut-être lui donner du plaisir. Or il ne classait parmi celles-là que les rendez-vous avec des gens qu'il ne connaissait pas encore et que son ardente imagination lui représentait sans doute comme ayant une chance d'être différents des autres. Mais pour ceux qu'il connaissait déjà, il savait trop bien comment ils étaient, comment ils seraient, ils ne lui paraissaient plus valoir la peine d'une fatigue dangereuse pour lui et peut-être mortelle. C'était, en somme, un très mauvais ami. Et peut-être dans son goût pour des gens nouveaux se retrouvait-il quelque chose de l'audace frénétique qu'il portait jadis, à Balbec, aux sports, au jeu, à tous les excès de table. Quant à Mme Verdurin, elle voulait à chaque fois me faire faire la connaissance d'Andrée, ne pouvant admettre que je l'eusse connue depuis longtemps. D'ailleurs Andrée venait rarement avec son mari, mais elle était pour moi une amie admirable et sincère. Fidèle à l'esthétique de son mari, qui était en réaction contre les Ballets russes, elle disait du marquis de Polignac : « Il a sa maison décorée par Bakst ; comment peut-on dormir là dedans, j'aimerais mieux Dubufe. »\n\nD'ailleurs les M. Verdurin, par le progrès fatal de l'esthétisme, qui finit par se manger la queue, disaient ne pas pouvoir supporter le modern style (de plus c'était munichois) ni les appartements blancs et n'aimaient plus que les vieux meubles français dans un décor sombre.\n\nOn fut très étonné à cette époque, où Mme Verdurin pouvait avoir chez elle qui elle voulait, de lui voir faire indirectement des avances à une personne qu'elle avait complètement perdue de vue, Odette. On trouvait qu'elle ne pourrait rien ajouter au brillant milieu qu'était devenu le petit groupe. Mais une séparation prolongée, en même temps qu'elle apaise les rancunes, réveille quelquefois l'amitié. Et puis le phénomène qui amène non seulement les mourants à ne prononcer que des noms autrefois familiers, mais les vieillards à se complaire dans leurs souvenirs d'enfance, ce phénomène a son équivalent social. Pour réussir dans l'entreprise de faire revenir Odette chez elle, Mme Verdurin n'employa pas, bien entendu, les « ultras », mais les habitués moins fidèles qui avaient gardé un pied dans l'un et l'autre salon. Elle leur disait : « Je ne sais pas pourquoi on ne la voit plus ici. Elle est peut-être brouillée, moi pas. En somme, qu'est-ce que je lui ai fait ? C'est chez moi qu'elle a connu ses deux maris. Si elle veut revenir, qu'elle sache que les portes lui sont ouvertes. » Ces paroles, qui auraient dû coûter à la fierté de la Patronne si elles ne lui avaient pas été dictées par son imagination, furent redites, mais sans succès. Mme Verdurin attendit Odette sans la voir venir, jusqu'à ce que des événements qu'on verra plus loin amenassent pour de tout autres raisons ce que n'avait pu l'ambassade pourtant zélée des lâcheurs. Tant il est peu de réussites faciles, et d'échecs définitifs.\n\nLes choses étaient tellement les mêmes, tout en paraissant différentes, qu'on retrouvait tout naturellement les mots d'autrefois : « bien pensants, mal pensants ». Et de même que les anciens communards avaient été antirévisionnistes, les plus grands dreyfusards voulaient faire fusiller tout le monde et avaient l'appui des généraux, comme ceux-ci au temps de l'affaire avaient été contre Galliffet. À ces réunions, Mme Verdurin invitait quelques dames un peu récentes, connues par les oeuvres et qui les premières fois venaient avec des toilettes éclatantes, de grands colliers de perles qu'Odette, qui en avait un aussi beau, de l'exhibition duquel elle-même avait abusé, regardait, maintenant qu'elle était en « tenue de guerre » à l'imitation des dames du faubourg, avec sévérité. Mais les femmes savent s'adapter. Au bout de trois ou quatre fois elles se rendaient compte que les toilettes qu'elles avaient crues chic étaient précisément proscrites par les personnes qui l'étaient, elles mettaient de côté leurs robes d'or et se résignaient à la simplicité.\n\nMme Verdurin disait : « C'est désolant, je vais téléphoner à Bontemps de faire le nécessaire pour demain, on a encore « caviardé » toute la fin de l'article de Norpois et simplement parce qu'il laissait entendre qu'on avait « limogé » Percin. » Car la bêtise courante faisait que chacun tirait sa gloire d'user des expressions courantes, et croyait montrer qu'elle était ainsi à la mode comme faisait une bourgeoise en disant, quand on parlait de M. de marquis de Bréauté ou de baron de Charlus : « Qui ? Bebel de marquis de Bréauté, Mémé de baron de Charlus ? » Les duchesses font de même, d'ailleurs, et avaient le même plaisir à dire « limoger » car, chez les duchesses, c'est, pour les roturiers un peu poètes, le nom qui diffère, mais elles s'expriment selon la catégorie d'esprit à laquelle elles appartiennent et où il y a aussi énormément de bourgeois. Les classes d'esprit n'ont pas égard à la naissance.",
  "reader_urls": {
    "fr-original": "https://nathanbrixius.com/projects/islt/fr-original/v7-p2-m-de-charlus-pendant-la-guerre#p-11",
    "en-moncrieff": "https://nathanbrixius.com/projects/islt/en-moncrieff/v7-p2-m-de-charlus-pendant-la-guerre#p-11"
  },
  "source_chapter_range": {
    "start": "437",
    "end": "455"
  },
  "alias_map": {
    "Swann": {
      "aliases": [
        "Swann",
        "M. Swann",
        "Charles Swann"
      ],
      "notes": "Charles Swann"
    },
    "Legrandin": {
      "aliases": [
        "Legrandin",
        "M. Legrandin"
      ],
      "notes": ""
    },
    "Mme de Villeparisis": {
      "aliases": [
        "Mme de Villeparisis",
        "Madame de Villeparisis"
      ],
      "notes": ""
    },
    "Mme de Cambremer": {
      "aliases": [
        "Mme de Cambremer",
        "Madame de Cambremer"
      ],
      "notes": "Legrandin's sister"
    },
    "M. Vinteuil": {
      "aliases": [
        "M. Vinteuil",
        "Vinteuil"
      ],
      "notes": ""
    },
    "la mère du narrateur": {
      "aliases": [
        "maman",
        "ma mère"
      ],
      "notes": ""
    },
    "Odette": {
      "aliases": [
        "Odette",
        "Odette de Crécy",
        "Odette de Crecy",
        "Mme de Crécy",
        "Mme de Crecy"
      ],
      "notes": "Odette de Crecy; later Mme Swann"
    },
    "Mme Verdurin": {
      "aliases": [
        "Mme Verdurin",
        "Madame Verdurin"
      ],
      "notes": "Verdurin salon hostess"
    },
    "M. Verdurin": {
      "aliases": [
        "M. Verdurin",
        "Monsieur Verdurin",
        "Verdurin"
      ],
      "notes": "Verdurin salon host"
    },
    "comte de Forcheville": {
      "aliases": [
        "Forcheville",
        "comte de Forcheville",
        "M. de Forcheville"
      ],
      "notes": "Aristocratic newcomer to the Verdurin circle"
    },
    "Brichot": {
      "aliases": [
        "Brichot",
        "M. Brichot"
      ],
      "notes": "Professor associated with the Verdurin circle"
    },
    "docteur Cottard": {
      "aliases": [
        "Cottard",
        "docteur Cottard",
        "le docteur"
      ],
      "notes": "Verdurin regular known for literal-minded wit"
    },
    "Mme Cottard": {
      "aliases": [
        "Mme Cottard",
        "Madame Cottard"
      ],
      "notes": "Wife of docteur Cottard"
    },
    "Saniette": {
      "aliases": [
        "Saniette"
      ],
      "notes": "Verdurin circle hanger-on"
    },
    "le peintre": {
      "aliases": [
        "le peintre",
        "peintre"
      ],
      "notes": "Verdurin circle painter"
    },
    "marquis de Forestelle": {
      "aliases": [
        "marquis de Forestelle",
        "M. de Forestelle",
        "Forestelle"
      ],
      "notes": "Swann acquaintance with a nearby estate"
    },
    "baron de Charlus": {
      "aliases": [
        "baron de Charlus",
        "Charlus"
      ],
      "notes": "Aristocratic social connection mentioned in Swann's prestige world"
    },
    "oncle Adolphe": {
      "aliases": [
        "mon oncle Adolphe",
        "oncle Adolphe",
        "Adolphe"
      ],
      "notes": "Narrator's uncle Adolphe"
    },
    "marquise de Saint-Euverte": {
      "aliases": [
        "marquise de Saint-Euverte",
        "Mme de Saint-Euverte",
        "Saint-Euverte"
      ],
      "notes": "Parisian salon hostess"
    },
    "général de Froberville": {
      "aliases": [
        "général de Froberville",
        "general de Froberville",
        "Froberville"
      ],
      "notes": "Worldly acquaintance in Swann's social circle"
    },
    "marquis de Bréauté": {
      "aliases": [
        "marquis de Bréauté",
        "marquis de Breaute",
        "Bréauté",
        "Breaute"
      ],
      "notes": "Worldly acquaintance in Swann's social circle"
    },
    "marquise de Gallardon": {
      "aliases": [
        "marquise de Gallardon",
        "Mme de Gallardon",
        "Gallardon"
      ],
      "notes": "Guermantes relation obsessed with rank and kinship display"
    },
    "duc de Guermantes": {
      "aliases": [
        "duc de Guermantes"
      ],
      "notes": "Guermantes aristocrat referenced in the Laumes social orbit"
    },
    "princesse de Parme": {
      "aliases": [
        "princesse de Parme"
      ],
      "notes": "Aristocratic hostess in the Guermantes orbit"
    },
    "M. d'Orsan": {
      "aliases": [
        "M. d'Orsan",
        "d'Orsan",
        "Orsan"
      ],
      "notes": "Swann social acquaintance considered among suspects"
    },
    "Rémi": {
      "aliases": [
        "Rémi",
        "Remi"
      ],
      "notes": "Swann associate/servant mentioned among suspects"
    },
    "comtesse de Monteriender": {
      "aliases": [
        "comtesse de Monteriender",
        "Mme de Monteriender",
        "Monteriender"
      ],
      "notes": "Salon attendee who comments after the sonata"
    },
    "Napoléon III": {
      "aliases": [
        "Napoléon III",
        "Napoleon III"
      ],
      "notes": "Dream-figure standing in for Forcheville in Swann's dream"
    },
    "Gilberte": {
      "aliases": [
        "Gilberte"
      ],
      "notes": "Gilberte Swann, first encountered at the Champs-Elysees"
    },
    "Françoise": {
      "aliases": [
        "Françoise",
        "Francoise"
      ],
      "notes": "Narrator's family servant"
    },
    "la Berma": {
      "aliases": [
        "la Berma",
        "Berma"
      ],
      "notes": "Celebrated actress"
    },
    "Bergotte": {
      "aliases": [
        "Bergotte"
      ],
      "notes": "Writer admired by the narrator"
    },
    "Norpois": {
      "aliases": [
        "Norpois",
        "M. de Norpois",
        "le marquis de Norpois"
      ],
      "notes": "Marquis de Norpois, diplomat and family dinner guest"
    },
    "la grand-mère": {
      "aliases": [
        "ma grand-mère",
        "grand-mère",
        "ma grand'mère",
        "grand'mère",
        "la grand-mère"
      ],
      "notes": "Narrator's grandmother"
    },
    "M. de Stermaria": {
      "aliases": [
        "M. de Stermaria",
        "de Stermaria",
        "Stermaria"
      ],
      "notes": "Aristocratic hotel guest at Balbec"
    },
    "Aimé": {
      "aliases": [
        "Aimé",
        "Aime"
      ],
      "notes": "Headwaiter or maître d'hôtel at the Grand-Hôtel in Balbec"
    },
    "Mlle de Stermaria": {
      "aliases": [
        "Mlle de Stermaria"
      ],
      "notes": "Daughter of M. de Stermaria"
    },
    "marquis de Cambremer": {
      "aliases": [
        "marquis de Cambremer",
        "M. de Cambremer"
      ],
      "notes": "Male member of the Cambremer family in the Balbec hotel circle"
    },
    "princesse de Luxembourg": {
      "aliases": [
        "princesse de Luxembourg",
        "La princesse de Luxembourg"
      ],
      "notes": "Aristocratic visitor in the Balbec social scene"
    },
    "le père du narrateur": {
      "aliases": [
        "mon père",
        "votre père"
      ],
      "notes": "Narrator's father"
    },
    "Mme Blandais": {
      "aliases": [
        "Mme Blandais",
        "Madame Blandais"
      ],
      "notes": "Member of the Balbec gossip circle"
    },
    "Mme Poncin": {
      "aliases": [
        "Mme Poncin",
        "Madame Poncin"
      ],
      "notes": "Member of the Balbec gossip circle"
    },
    "Robert de Saint-Loup": {
      "aliases": [
        "Saint-Loup",
        "Robert de Saint-Loup",
        "marquis de Saint-Loup-en-Bray",
        "le neveu de Mme de Villeparisis"
      ],
      "notes": "Young aristocrat and nephew of Mme de Villeparisis"
    },
    "M. de Marsantes": {
      "aliases": [
        "M. de Marsantes",
        "Marsantes",
        "Saint-Loup de Saint-Loup"
      ],
      "notes": "Father of Saint-Loup"
    },
    "Bloch": {
      "aliases": [
        "Bloch",
        "Bloch fils"
      ],
      "notes": "Friend/acquaintance of the narrator; socially performative and often ironic"
    },
    "prince des Laumes": {
      "aliases": [
        "prince des Laumes"
      ],
      "notes": "Guermantes title in the family sequence discussed with Saint-Loup"
    },
    "Bloch père": {
      "aliases": [
        "Bloch père"
      ],
      "notes": "Bloch's father as remembered and socially evaluated in the narrator's reflections"
    },
    "le directeur": {
      "aliases": [
        "le directeur",
        "directeur"
      ],
      "notes": "Grand-Hotel director observed by the narrator"
    },
    "Dreyfus": {
      "aliases": [
        "Dreyfus"
      ],
      "notes": "Figure invoked in the political talk reported by Aimé"
    },
    "jeune blonde de Rivebelle": {
      "aliases": [
        "jeune blonde",
        "jeune blonde à l'air triste"
      ],
      "notes": "The sad-looking blonde seen at Rivebelle who begins to crystallize in the narrator's desire"
    },
    "duchesse de Guermantes": {
      "aliases": [
        "duchesse de Guermantes",
        "Mme de Guermantes",
        "Madame de Guermantes",
        "la duchesse"
      ],
      "notes": "Oriane de Guermantes; now appearing as the duchesse de Guermantes"
    },
    "Jupien": {
      "aliases": [
        "Jupien"
      ],
      "notes": "Neighbor and ally of Françoise in the new Guermantes setting"
    },
    "princesse de Guermantes": {
      "aliases": [
        "princesse de Guermantes",
        "princesse de Guermantes-Bavière",
        "Mme de Guermantes-Bavière"
      ],
      "notes": "Princesse de Guermantes-Bavière; hostess of the evening in the opening of v4-p2"
    },
    "duc de Châtellerault": {
      "aliases": [
        "duc de Châtellerault",
        "M. de Châtellerault",
        "Châtellerault"
      ],
      "notes": "Aristocratic young man encountered outside the princesse de Guermantes salon"
    },
    "M. de Vaugoubert": {
      "aliases": [
        "M. de Vaugoubert",
        "Vaugoubert"
      ],
      "notes": "Diplomat/ambassador figure appearing in the princesse de Guermantes salon"
    },
    "Mme de Vaugoubert": {
      "aliases": [
        "Mme de Vaugoubert",
        "Madame de Vaugoubert"
      ],
      "notes": "Wife of M. de Vaugoubert"
    },
    "Albertine": {
      "aliases": [
        "Albertine"
      ],
      "notes": "Albertine Simonet; narrator's companion in La Prisonnière"
    },
    "Andrée": {
      "aliases": [
        "Andrée",
        "Andree"
      ],
      "notes": "Andrée, one of the Balbec girls and Albertine's friend"
    },
    "Mme Bontemps": {
      "aliases": [
        "Mme Bontemps",
        "Madame Bontemps"
      ],
      "notes": "Albertine's aunt"
    },
    "Morel": {
      "aliases": [
        "Morel"
      ],
      "notes": "Charles Morel, violinist associated with Charlus and the Verdurins"
    },
    "Elstir": {
      "aliases": [
        "Elstir"
      ],
      "notes": "Painter and social/aesthetic authority referenced by Albertine."
    },
    "prince de Léon": {
      "aliases": [
        "prince de Léon",
        "prince de Leon",
        "Léon",
        "Leon"
      ],
      "notes": "Prince de Leon, beau-frere de Saint-Loup in the duchesse de Guermantes anecdotes."
    },
    "marquis du Lau": {
      "aliases": [
        "marquis du Lau",
        "du Lau"
      ],
      "notes": "Aristocratic figure in the duchesse de Guermantes reminiscences."
    },
    "Mme de Chaussepierre": {
      "aliases": [
        "Mme de Chaussepierre",
        "Madame de Chaussepierre",
        "Chaussepierre"
      ],
      "notes": "Social rival figure in the Jockey Club episode around the Guermantes."
    }
  },
  "prior_context": "M. Bontemps ne voulait pas entendre parler de paix avant que l'Allemagne eût été réduite au même morcellement qu'au moyen âge, la déchéance de la maison de Hohenzollern prononcée, Guillaume ayant reçu douze balles dans la peau. En un mot, il était ce que Brichot appelait un « Jusquauboutiste », c'était le meilleur brevet de civisme qu'on pouvait lui donner. Sans doute, les trois premiers jours, Mme Bontemps avait été un peu dépaysée au milieu des personnes qui avaient demandé à Mme Verdurin à la connaître, et ce fut d'un ton légèrement aigre que Mme Verdurin répondit : « Le comte, ma chère », à Mme Bontemps qui lui disait : « C'est bien le duc d'Haussonville que vous venez de me présenter », soit par entière ignorance et absence de toute association entre le nom Haussonville et un titre quelconque, soit, au contraire, par excessive instruction et association d'idées avec le « Parti des Ducs », dont on lui avait dit que M. d'Haussonville était un des membres à l'Académie. À partir du quatrième jour elle avait commencé d'être solidement installée dans le faubourg Saint-Germain. Quelquefois encore on voyait autour d'elle les fragments inconnus d'un monde qu'on ne connaissait pas et qui n'étonnaient pas plus que des débris de coquille autour du poussin, ceux qui savaient l'oeuf d'où Mme Bontemps était sortie. Mais dès le quinzième jour, elle les avait secoués, et avant la fin du premier mois, quand elle disait : « Je vais chez les Lévi », tout le monde comprenait, sans qu'elle eût besoin de préciser, qu'il s'agissait des Lévis-Mirepoix, et pas une duchesse ne se serait couchée sans avoir appris de Mme Bontemps ou de Mme Verdurin, au moins par téléphone, ce qu'il y avait dans le communiqué du soir, ce qu'on y avait omis, où on en était avec la Grèce, quelle offensive on préparait, en un mot tout ce que le public ne saurait que le lendemain ou plus tard, et dont on avait ainsi comme une sorte de répétition des couturières. Dans la conversation, Mme Verdurin, pour communiquer les nouvelles, disait : « nous » en parlant de la France. « Hé bien, voici : nous exigeons du roi de Grèce qu'il se retire du Péloponèse, etc. ; nous lui envoyons, etc. » Et dans tous ses récits revenait tout le temps le G.Q.G. (j'ai téléphoné au G.Q.G.), abréviation qu'elle avait à prononcer le même plaisir qu'avaient naguère les femmes qui ne connaissaient pas le prince d'Agrigente à demander en souriant, quand on parlait de lui et pour montrer qu'elles étaient au courant : « Grigri ? », un plaisir qui dans les époques peu troublées n'est connu que par les mondains, mais que dans ces grandes crises le peuple même connaît. Notre maître d'hôtel, par exemple, si on parlait du roi de Grèce, était capable, grâce aux journaux, de dire comme Guillaume II : « Tino », tandis que jusque-là sa familiarité avec les rois était restée plus vulgaire, ayant été inventée par lui, comme quand jadis, pour parler du Roi d'Espagne, il disait : « Fonfonse ». On peut remarquer, d'ailleurs, qu'au fur et à mesure qu'augmenta le nombre des gens brillants qui firent des avances à Mme Verdurin, le nombre de ceux qu'elle appelait les « ennuyeux » diminua. Par une sorte de transformation magique, tout ennuyeux qui était venu lui faire une visite et avait sollicité une invitation devenait subitement quelqu'un d'agréable, d'intelligent. Bref, au bout d'un an le nombre des ennuyeux était réduit dans une proportion tellement forte, que la « peur et l'impossibilité de s'ennuyer », qui avait tenu une si grande place dans la conversation et joué un si grand rôle dans la vie de Mme Verdurin, avait presque entièrement disparu. On eût dit que sur le tard cette impossibilité de s'ennuyer (qu'autrefois, d'ailleurs, elle assurait ne pas avoir éprouvée dans sa prime jeunesse) la faisait moins souffrir, comme certaines migraines, certains asthmes nerveux qui perdent de leur force quand on vieillit. Et l'effroi de s'ennuyer eût sans doute entièrement abandonné Mme Verdurin, faute d'ennuyeux, si elle n'avait, dans une faible mesure, remplacé ceux qui ne l'étaient plus par d'autres recrutés parmi les anciens fidèles. Du reste, pour en finir avec les duchesses qui fréquentaient maintenant chez Mme Verdurin, elles venaient y chercher, sans qu'elles s'en doutassent, exactement la même chose que les dreyfusards autrefois, c'est-à-dire un plaisir mondain composé de telle manière que sa dégustation assouvît les curiosités politiques et rassasiât le besoin de commenter entre soi les incidents lus dans les journaux. Mme Verdurin disait : « Vous viendrez à 5 heures parler de la guerre », comme autrefois « parler de l'affaire », et dans l'intervalle : « Vous viendrez entendre Morel ». Or Morel n'aurait pas dû être là, pour la raison qu'il n'était nullement réformé. Simplement il n'avait pas rejoint et était déserteur, mais personne ne le savait. Une autre étoile du salon était « dans les choux », qui malgré ses goûts sportifs s'était fait réformer. Il était devenu tellement pour moi l'auteur d'une oeuvre admirable à laquelle je pensais constamment que ce n'est que par hasard, quand j'établissais un courant transversal entre deux séries de souvenirs, que je songeais qu'il était celui qui avait amené le départ d'Albertine de chez moi. Et encore ce courant transversal aboutissait, en ce qui concernait ces reliques de souvenirs d'Albertine, à une voie s'arrêtant en pleine friche à plusieurs années de distance. Car je ne pensais plus jamais à elle. C'était une voie non fréquentée de souvenirs, une ligne que je n'empruntais plus. Tandis que les oeuvres de « dans les choux » étaient récentes et cette ligne de souvenirs perpétuellement fréquentée et utilisée par mon esprit."
}
